bork/__init__.py
bork/__main__.py
bork/api.py
bork/asset_manager.py
bork/builder.py
bork/cli.py
bork/filesystem.py
bork/github.py
bork/github_api.py
bork/http.py
bork/log.py
bork/pypi.py
bork/pypi_api.py
bork/version.py
bork-9.0.0.dist-info/LICENSE.txt
bork-9.0.0.dist-info/METADATA
bork-9.0.0.dist-info/WHEEL
bork-9.0.0.dist-info/entry_points.txt
bork-9.0.0.dist-info/top_level.txt
bork-9.0.0.dist-info/RECORD
