Metadata-Version: 2.1
Name: bork
Version: 9.0.0
Summary: A program to help build, maintain, and release PEP 517-compliant projects.
Author-email: Ellen Marie Dash <me@duckie.co>
License: MIT
Project-URL: repository, https://github.com/duckinator/bork
Project-URL: documentation, https://bork.readthedocs.io/en/latest/
Classifier: Programming Language :: Python :: 3
Classifier: Programming Language :: Python :: 3.8
Classifier: Programming Language :: Python :: 3.9
Classifier: Programming Language :: Python :: 3.10
Classifier: Programming Language :: Python :: 3.11
Classifier: License :: OSI Approved :: MIT License
Classifier: Operating System :: OS Independent
Requires-Python: >=3.8
License-File: LICENSE.txt
Requires-Dist: build ~=1.2.1
Requires-Dist: packaging ~=23.2
Requires-Dist: coloredlogs ~=15.0.1
Requires-Dist: urllib3 ~=2.2.2
Requires-Dist: pip
Requires-Dist: importlib-metadata ; python_version < "3.10"
Requires-Dist: toml ~=0.10.2 ; python_version < "3.11"
Provides-Extra: docs
Requires-Dist: sphinx ; extra == 'docs'
Requires-Dist: sphinx-rtd-theme ; extra == 'docs'
Requires-Dist: sphinx-argparse ; extra == 'docs'
Provides-Extra: lint
Requires-Dist: ruff ; extra == 'lint'
Requires-Dist: mypy ==1.5.1 ; extra == 'lint'
Provides-Extra: test
Requires-Dist: pytest ==7.4.2 ; extra == 'test'
Requires-Dist: setuptools >=61 ; extra == 'test'
Requires-Dist: wheel ; extra == 'test'
